{"kind":"identitytoolkit#DownloadAccountResponse","users":[{"localId":"BnIEizXy8syRyeMBlMjjIaOoe3Cm","createdAt":"1667315683406","lastLoginAt":"1669703235633","displayName":"","photoUrl":"","passwordHash":"fakeHash:salt=fakeSaltIVWyzVwbNJ1PiYgCPS5j:password=yyyyyyyy","salt":"fakeSaltIVWyzVwbNJ1PiYgCPS5j","passwordUpdatedAt":1669705030493,"providerUserInfo":[{"providerId":"password","email":"y@yas.com","federatedId":"y@yas.com","rawId":"y@yas.com","displayName":"","photoUrl":""}],"validSince":"1669705030","email":"y@yas.com","emailVerified":false,"disabled":false},{"localId":"bMNrLS7xUcBT3e2iHFhoeu77KO7n","createdAt":"1667315701782","lastLoginAt":"1669705084815","displayName":"","photoUrl":"","passwordHash":"fakeHash:salt=fakeSaltlRBv5Q2szKKqWRdYp0di:password=mmmmmmmm","salt":"fakeSaltlRBv5Q2szKKqWRdYp0di","passwordUpdatedAt":1669705030493,"providerUserInfo":[{"providerId":"password","email":"m@maro.com","federatedId":"m@maro.com","rawId":"m@maro.com","displayName":"","photoUrl":""}],"validSince":"1669705030","email":"m@maro.com","emailVerified":false,"disabled":false,"lastRefreshAt":"2022-11-29T06:58:04.815Z"},{"localId":"vR2iVO2eJg2VkcZMkMEa5CLeIJmn","createdAt":"1667315664434","lastLoginAt":"1669705049016","displayName":"","photoUrl":"","passwordHash":"fakeHash:salt=fakeSaltkQHIOLKvlbh41vVT50CC:password=tttttttt","salt":"fakeSaltkQHIOLKvlbh41vVT50CC","passwordUpdatedAt":1669705030494,"providerUserInfo":[{"providerId":"password","email":"t@takkun.com","federatedId":"t@takkun.com","rawId":"t@takkun.com","displayName":"","photoUrl":""}],"validSince":"1669705030","email":"t@takkun.com","emailVerified":false,"disabled":false,"lastRefreshAt":"2022-11-29T06:57:29.016Z"}]}